{
	"name": "Girafarig",
	"nationalId": 203,
	"types": [
		"normal",
		"psychic"
	],
	"abilities": [
		{
			"name": "Inner Focus"
		},
		{
			"name": "Sap Sipper",
			"hidden": true
		}
	],
	"genderRatios": {
		"male": 50,
		"female": 50
	},
	"catchRate": 60,
	"eggGroups": [
		"Field"
	],
	"hatchTime": [
		5355,
		5609
	],
	"height": "4'11\"",
	"weight": "41.5 kg",
	"baseExpYield": 159,
	"levelingRate": "Medium Fast",
	"evYield": {
		"hp": 0,
		"atk": 0,
		"def": 0,
		"spa": 2,
		"spd": 0,
		"spe": 0
	},
	"color": "Yellow",
	"baseFriendship": 70,
	"baseStats": {
		"hp": 70,
		"atk": 80,
		"def": 65,
		"spa": 90,
		"spd": 65,
		"spe": 85
	},
	"evolutionFrom": null,
	"evolutions": [],
	"megaEvolutions": [],
	"categories": "Long Neck Pokémon",
	"regionIds": {
		"kanto": null,
		"johto": 149,
		"hoenn": 171,
		"sinnoh": 121,
		"unova": null,
		"kalos": null,
		"alola": null
	},
	"pokedexEntries": {
		"gold": "Its tail has a small brain of its own. Beware! If you get close, it may react to your scent and bite.",
		"silver": "Its tail, which also contains a small brain, may bite on its own if it notices an alluring smell.",
		"crystal": "When it is in danger, its tail uses some sort of mysterious powers to drive away the enemy.",
		"ruby": "Girafarig's rear head also has a brain, but it is small. The rear head attacks in response to smells and sounds. Approaching this Pokémon from behind can cause the rear head to suddenly lash out and bite.",
		"sapphire": "Girafarig's rear head contains a tiny brain that is too small for thinking. However, the rear head doesn't need to sleep, so it can keep watch over its surroundings 24 hours a day.",
		"emerald": "A Girafarig is an herbivore—it eats grass and tree shoots. While it is eating, its tail makes chewing and swallowing motions as if it were also eating.",
		"fireRed": "Its tail, which also contains a small brain, may bite on its own if it notices an alluring smell.",
		"leafGreen": "Its tail has a small brain of its own. Beware! If you get close, it may react to your scent and bite.",
		"diamond": "Its tail also has a small brain. It bites to repel any foe trying to sneak up on it from behind.",
		"pearl": "While it sleeps, the head on its tail keeps watch. The tail doesn't need to sleep.",
		"platinum": "The head on its tail contains a small brain. It can instinctively fight even while facing backward.",
		"heartGold": "Its tail has a small brain of its own. Beware! If you get close, it may react to your scent and bite.",
		"soulSilver": "Its tail, which also contains a small brain, may bite on its own if it notices an alluring smell.",
		"black": "The head on its tail contains a small brain. It can instinctively fight even while facing backward.",
		"white": "The head on its tail contains a small brain. It can instinctively fight even while facing backward.",
		"black2": "The head on its tail contains a small brain. It can instinctively fight even while facing backward.",
		"white2": "The head on its tail contains a small brain. It can instinctively fight even while facing backward.",
		"x": "While it sleeps, the head on its tail keeps watch. The tail doesn't need to sleep.",
		"y": "Its tail has a small brain of its own. Beware! If you get close, it may react to your scent by biting.",
		"omegaRuby": "Girafarig's rear head also has a brain, but it is small. The rear head attacks in response to smells and sounds. Approaching this Pokémon from behind can cause the rear head to suddenly lash out and bite.",
		"alphaSapphire": "Girafarig's rear head contains a tiny brain that is too small for thinking. However, the rear head doesn't need to sleep, so it can keep watch over its surroundings 24 hours a day."
	},
	"pokeathlonStats": {
		"speed": [
			3,
			4
		],
		"power": [
			3,
			4
		],
		"stamina": [
			2,
			3
		],
		"skill": [
			3,
			4
		],
		"jump": [
			2,
			3
		]
	},
	"ultraAlolaId": null,
	"moveLearnSets": [
		{
			"games": [
				"Gold",
				"Silver"
			],
			"learnset": [
				{
					"move": "Confusion",
					"level": 1
				},
				{
					"move": "Growl",
					"level": 1
				},
				{
					"move": "Stomp",
					"level": 1
				},
				{
					"move": "Tackle",
					"level": 1
				},
				{
					"move": "Confusion",
					"level": 7
				},
				{
					"move": "Stomp",
					"level": 13
				},
				{
					"move": "Agility",
					"level": 20
				},
				{
					"move": "Baton Pass",
					"level": 30
				},
				{
					"move": "Psybeam",
					"level": 41
				},
				{
					"move": "Crunch",
					"level": 54
				},
				{
					"move": "Amnesia",
					"egg_move": true
				},
				{
					"move": "Beat Up",
					"egg_move": true
				},
				{
					"move": "Foresight",
					"egg_move": true
				},
				{
					"move": "Future Sight",
					"egg_move": true
				},
				{
					"move": "Take Down",
					"egg_move": true
				},
				{
					"move": "Strength",
					"tm": "HM4"
				},
				{
					"move": "Headbutt",
					"tm": "TM2"
				},
				{
					"move": "Curse",
					"tm": "TM3"
				},
				{
					"move": "Toxic",
					"tm": "TM6"
				},
				{
					"move": "Zap Cannon",
					"tm": "TM7"
				},
				{
					"move": "Rock Smash",
					"tm": "TM8"
				},
				{
					"move": "Psych Up",
					"tm": "TM9"
				},
				{
					"move": "Hidden Power",
					"tm": "TM10"
				},
				{
					"move": "Sunny Day",
					"tm": "TM11"
				},
				{
					"move": "Snore",
					"tm": "TM13"
				},
				{
					"move": "Protect",
					"tm": "TM17"
				},
				{
					"move": "Endure",
					"tm": "TM20"
				},
				{
					"move": "Frustration",
					"tm": "TM21"
				},
				{
					"move": "Iron Tail",
					"tm": "TM23"
				},
				{
					"move": "Thunder",
					"tm": "TM25"
				},
				{
					"move": "Earthquake",
					"tm": "TM26"
				},
				{
					"move": "Return",
					"tm": "TM27"
				},
				{
					"move": "Psychic",
					"tm": "TM29"
				},
				{
					"move": "Shadow Ball",
					"tm": "TM30"
				},
				{
					"move": "Mud-Slap",
					"tm": "TM31"
				},
				{
					"move": "Double Team",
					"tm": "TM32"
				},
				{
					"move": "Swagger",
					"tm": "TM34"
				},
				{
					"move": "Sleep Talk",
					"tm": "TM35"
				},
				{
					"move": "Swift",
					"tm": "TM39"
				},
				{
					"move": "Dream Eater",
					"tm": "TM42"
				},
				{
					"move": "Rest",
					"tm": "TM44"
				},
				{
					"move": "Attract",
					"tm": "TM45"
				},
				{
					"move": "Thief",
					"tm": "TM46"
				},
				{
					"move": "Nightmare",
					"tm": "TM50"
				}
			]
		},
		{
			"games": [
				"Crystal"
			],
			"learnset": [
				{
					"move": "Confusion",
					"level": 1
				},
				{
					"move": "Growl",
					"level": 1
				},
				{
					"move": "Stomp",
					"level": 1
				},
				{
					"move": "Tackle",
					"level": 1
				},
				{
					"move": "Confusion",
					"level": 7
				},
				{
					"move": "Stomp",
					"level": 13
				},
				{
					"move": "Agility",
					"level": 20
				},
				{
					"move": "Baton Pass",
					"level": 30
				},
				{
					"move": "Psybeam",
					"level": 41
				},
				{
					"move": "Crunch",
					"level": 54
				},
				{
					"move": "Amnesia",
					"egg_move": true
				},
				{
					"move": "Beat Up",
					"egg_move": true
				},
				{
					"move": "Foresight",
					"egg_move": true
				},
				{
					"move": "Future Sight",
					"egg_move": true
				},
				{
					"move": "Take Down",
					"egg_move": true
				},
				{
					"move": "Strength",
					"tm": "HM4"
				},
				{
					"move": "Headbutt",
					"tm": "TM2"
				},
				{
					"move": "Curse",
					"tm": "TM3"
				},
				{
					"move": "Toxic",
					"tm": "TM6"
				},
				{
					"move": "Zap Cannon",
					"tm": "TM7"
				},
				{
					"move": "Rock Smash",
					"tm": "TM8"
				},
				{
					"move": "Psych Up",
					"tm": "TM9"
				},
				{
					"move": "Hidden Power",
					"tm": "TM10"
				},
				{
					"move": "Sunny Day",
					"tm": "TM11"
				},
				{
					"move": "Snore",
					"tm": "TM13"
				},
				{
					"move": "Protect",
					"tm": "TM17"
				},
				{
					"move": "Endure",
					"tm": "TM20"
				},
				{
					"move": "Frustration",
					"tm": "TM21"
				},
				{
					"move": "Iron Tail",
					"tm": "TM23"
				},
				{
					"move": "Thunder",
					"tm": "TM25"
				},
				{
					"move": "Earthquake",
					"tm": "TM26"
				},
				{
					"move": "Return",
					"tm": "TM27"
				},
				{
					"move": "Psychic",
					"tm": "TM29"
				},
				{
					"move": "Shadow Ball",
					"tm": "TM30"
				},
				{
					"move": "Mud-Slap",
					"tm": "TM31"
				},
				{
					"move": "Double Team",
					"tm": "TM32"
				},
				{
					"move": "Swagger",
					"tm": "TM34"
				},
				{
					"move": "Sleep Talk",
					"tm": "TM35"
				},
				{
					"move": "Swift",
					"tm": "TM39"
				},
				{
					"move": "Dream Eater",
					"tm": "TM42"
				},
				{
					"move": "Rest",
					"tm": "TM44"
				},
				{
					"move": "Attract",
					"tm": "TM45"
				},
				{
					"move": "Thief",
					"tm": "TM46"
				},
				{
					"move": "Nightmare",
					"tm": "TM50"
				}
			]
		},
		{
			"games": [
				"Ruby",
				"Sapphire"
			],
			"learnset": [
				{
					"move": "Growl",
					"level": 1
				},
				{
					"move": "Tackle",
					"level": 1
				},
				{
					"move": "Astonish",
					"level": 7
				},
				{
					"move": "Confusion",
					"level": 13
				},
				{
					"move": "Stomp",
					"level": 19
				},
				{
					"move": "Odor Sleuth",
					"level": 25
				},
				{
					"move": "Agility",
					"level": 31
				},
				{
					"move": "Baton Pass",
					"level": 37
				},
				{
					"move": "Psybeam",
					"level": 43
				},
				{
					"move": "Crunch",
					"level": 49
				},
				{
					"move": "Amnesia",
					"egg_move": true
				},
				{
					"move": "Beat Up",
					"egg_move": true
				},
				{
					"move": "Foresight",
					"egg_move": true
				},
				{
					"move": "Future Sight",
					"egg_move": true
				},
				{
					"move": "Magic Coat",
					"egg_move": true
				},
				{
					"move": "Psych Up",
					"egg_move": true
				},
				{
					"move": "Take Down",
					"egg_move": true
				},
				{
					"move": "Wish",
					"egg_move": true
				},
				{
					"move": "Strength",
					"tm": "HM4"
				},
				{
					"move": "Flash",
					"tm": "HM5"
				},
				{
					"move": "Rock Smash",
					"tm": "HM6"
				},
				{
					"move": "Calm Mind",
					"tm": "TM4"
				},
				{
					"move": "Toxic",
					"tm": "TM6"
				},
				{
					"move": "Hidden Power",
					"tm": "TM10"
				},
				{
					"move": "Sunny Day",
					"tm": "TM11"
				},
				{
					"move": "Light Screen",
					"tm": "TM16"
				},
				{
					"move": "Protect",
					"tm": "TM17"
				},
				{
					"move": "Rain Dance",
					"tm": "TM18"
				},
				{
					"move": "Frustration",
					"tm": "TM21"
				},
				{
					"move": "Iron Tail",
					"tm": "TM23"
				},
				{
					"move": "Thunderbolt",
					"tm": "TM24"
				},
				{
					"move": "Thunder",
					"tm": "TM25"
				},
				{
					"move": "Earthquake",
					"tm": "TM26"
				},
				{
					"move": "Return",
					"tm": "TM27"
				},
				{
					"move": "Psychic",
					"tm": "TM29"
				},
				{
					"move": "Shadow Ball",
					"tm": "TM30"
				},
				{
					"move": "Double Team",
					"tm": "TM32"
				},
				{
					"move": "Reflect",
					"tm": "TM33"
				},
				{
					"move": "Shock Wave",
					"tm": "TM34"
				},
				{
					"move": "Facade",
					"tm": "TM42"
				},
				{
					"move": "Secret Power",
					"tm": "TM43"
				},
				{
					"move": "Rest",
					"tm": "TM44"
				},
				{
					"move": "Attract",
					"tm": "TM45"
				},
				{
					"move": "Thief",
					"tm": "TM46"
				},
				{
					"move": "Skill Swap",
					"tm": "TM48"
				}
			]
		},
		{
			"games": [
				"FireRed",
				"LeafGreen"
			],
			"learnset": [
				{
					"move": "Growl",
					"level": 1
				},
				{
					"move": "Tackle",
					"level": 1
				},
				{
					"move": "Astonish",
					"level": 7
				},
				{
					"move": "Confusion",
					"level": 13
				},
				{
					"move": "Stomp",
					"level": 19
				},
				{
					"move": "Odor Sleuth",
					"level": 25
				},
				{
					"move": "Agility",
					"level": 31
				},
				{
					"move": "Baton Pass",
					"level": 37
				},
				{
					"move": "Psybeam",
					"level": 43
				},
				{
					"move": "Crunch",
					"level": 49
				},
				{
					"move": "Amnesia",
					"egg_move": true
				},
				{
					"move": "Beat Up",
					"egg_move": true
				},
				{
					"move": "Foresight",
					"egg_move": true
				},
				{
					"move": "Future Sight",
					"egg_move": true
				},
				{
					"move": "Magic Coat",
					"egg_move": true
				},
				{
					"move": "Psych Up",
					"egg_move": true
				},
				{
					"move": "Take Down",
					"egg_move": true
				},
				{
					"move": "Wish",
					"egg_move": true
				},
				{
					"move": "Strength",
					"tm": "HM4"
				},
				{
					"move": "Flash",
					"tm": "HM5"
				},
				{
					"move": "Rock Smash",
					"tm": "HM6"
				},
				{
					"move": "Calm Mind",
					"tm": "TM4"
				},
				{
					"move": "Toxic",
					"tm": "TM6"
				},
				{
					"move": "Hidden Power",
					"tm": "TM10"
				},
				{
					"move": "Sunny Day",
					"tm": "TM11"
				},
				{
					"move": "Light Screen",
					"tm": "TM16"
				},
				{
					"move": "Protect",
					"tm": "TM17"
				},
				{
					"move": "Rain Dance",
					"tm": "TM18"
				},
				{
					"move": "Frustration",
					"tm": "TM21"
				},
				{
					"move": "Iron Tail",
					"tm": "TM23"
				},
				{
					"move": "Thunderbolt",
					"tm": "TM24"
				},
				{
					"move": "Thunder",
					"tm": "TM25"
				},
				{
					"move": "Earthquake",
					"tm": "TM26"
				},
				{
					"move": "Return",
					"tm": "TM27"
				},
				{
					"move": "Psychic",
					"tm": "TM29"
				},
				{
					"move": "Shadow Ball",
					"tm": "TM30"
				},
				{
					"move": "Double Team",
					"tm": "TM32"
				},
				{
					"move": "Reflect",
					"tm": "TM33"
				},
				{
					"move": "Shock Wave",
					"tm": "TM34"
				},
				{
					"move": "Facade",
					"tm": "TM42"
				},
				{
					"move": "Secret Power",
					"tm": "TM43"
				},
				{
					"move": "Rest",
					"tm": "TM44"
				},
				{
					"move": "Attract",
					"tm": "TM45"
				},
				{
					"move": "Thief",
					"tm": "TM46"
				},
				{
					"move": "Skill Swap",
					"tm": "TM48"
				}
			]
		},
		{
			"games": [
				"Emerald"
			],
			"learnset": [
				{
					"move": "Growl",
					"level": 1
				},
				{
					"move": "Tackle",
					"level": 1
				},
				{
					"move": "Astonish",
					"level": 7
				},
				{
					"move": "Confusion",
					"level": 13
				},
				{
					"move": "Stomp",
					"level": 19
				},
				{
					"move": "Odor Sleuth",
					"level": 25
				},
				{
					"move": "Agility",
					"level": 31
				},
				{
					"move": "Baton Pass",
					"level": 37
				},
				{
					"move": "Psybeam",
					"level": 43
				},
				{
					"move": "Crunch",
					"level": 49
				},
				{
					"move": "Amnesia",
					"egg_move": true
				},
				{
					"move": "Beat Up",
					"egg_move": true
				},
				{
					"move": "Foresight",
					"egg_move": true
				},
				{
					"move": "Future Sight",
					"egg_move": true
				},
				{
					"move": "Magic Coat",
					"egg_move": true
				},
				{
					"move": "Psych Up",
					"egg_move": true
				},
				{
					"move": "Take Down",
					"egg_move": true
				},
				{
					"move": "Wish",
					"egg_move": true
				},
				{
					"move": "Strength",
					"tm": "HM4"
				},
				{
					"move": "Flash",
					"tm": "HM5"
				},
				{
					"move": "Rock Smash",
					"tm": "HM6"
				},
				{
					"move": "Calm Mind",
					"tm": "TM4"
				},
				{
					"move": "Toxic",
					"tm": "TM6"
				},
				{
					"move": "Hidden Power",
					"tm": "TM10"
				},
				{
					"move": "Sunny Day",
					"tm": "TM11"
				},
				{
					"move": "Light Screen",
					"tm": "TM16"
				},
				{
					"move": "Protect",
					"tm": "TM17"
				},
				{
					"move": "Rain Dance",
					"tm": "TM18"
				},
				{
					"move": "Frustration",
					"tm": "TM21"
				},
				{
					"move": "Iron Tail",
					"tm": "TM23"
				},
				{
					"move": "Thunderbolt",
					"tm": "TM24"
				},
				{
					"move": "Thunder",
					"tm": "TM25"
				},
				{
					"move": "Earthquake",
					"tm": "TM26"
				},
				{
					"move": "Return",
					"tm": "TM27"
				},
				{
					"move": "Psychic",
					"tm": "TM29"
				},
				{
					"move": "Shadow Ball",
					"tm": "TM30"
				},
				{
					"move": "Double Team",
					"tm": "TM32"
				},
				{
					"move": "Reflect",
					"tm": "TM33"
				},
				{
					"move": "Shock Wave",
					"tm": "TM34"
				},
				{
					"move": "Facade",
					"tm": "TM42"
				},
				{
					"move": "Secret Power",
					"tm": "TM43"
				},
				{
					"move": "Rest",
					"tm": "TM44"
				},
				{
					"move": "Attract",
					"tm": "TM45"
				},
				{
					"move": "Thief",
					"tm": "TM46"
				},
				{
					"move": "Skill Swap",
					"tm": "TM48"
				}
			]
		},
		{
			"games": [
				"Diamond",
				"Pearl"
			],
			"learnset": [
				{
					"move": "Astonish",
					"level": 1
				},
				{
					"move": "Confusion",
					"level": 1
				},
				{
					"move": "Growl",
					"level": 1
				},
				{
					"move": "Guard Swap",
					"level": 1
				},
				{
					"move": "Power Swap",
					"level": 1
				},
				{
					"move": "Tackle",
					"level": 1
				},
				{
					"move": "Odor Sleuth",
					"level": 5
				},
				{
					"move": "Stomp",
					"level": 10
				},
				{
					"move": "Agility",
					"level": 14
				},
				{
					"move": "Psybeam",
					"level": 19
				},
				{
					"move": "Baton Pass",
					"level": 23
				},
				{
					"move": "Assurance",
					"level": 28
				},
				{
					"move": "Double Hit",
					"level": 32
				},
				{
					"move": "Psychic",
					"level": 37
				},
				{
					"move": "Zen Headbutt",
					"level": 41
				},
				{
					"move": "Crunch",
					"level": 46
				},
				{
					"move": "Amnesia",
					"egg_move": true
				},
				{
					"move": "Beat Up",
					"egg_move": true
				},
				{
					"move": "Double Kick",
					"egg_move": true
				},
				{
					"move": "Foresight",
					"egg_move": true
				},
				{
					"move": "Future Sight",
					"egg_move": true
				},
				{
					"move": "Magic Coat",
					"egg_move": true
				},
				{
					"move": "Mirror Coat",
					"egg_move": true
				},
				{
					"move": "Psych Up",
					"egg_move": true
				},
				{
					"move": "Take Down",
					"egg_move": true
				},
				{
					"move": "Wish",
					"egg_move": true
				},
				{
					"move": "Strength",
					"tm": "HM4"
				},
				{
					"move": "Rock Smash",
					"tm": "HM6"
				},
				{
					"move": "Calm Mind",
					"tm": "TM4"
				},
				{
					"move": "Toxic",
					"tm": "TM6"
				},
				{
					"move": "Hidden Power",
					"tm": "TM10"
				},
				{
					"move": "Sunny Day",
					"tm": "TM11"
				},
				{
					"move": "Light Screen",
					"tm": "TM16"
				},
				{
					"move": "Protect",
					"tm": "TM17"
				},
				{
					"move": "Rain Dance",
					"tm": "TM18"
				},
				{
					"move": "Frustration",
					"tm": "TM21"
				},
				{
					"move": "Iron Tail",
					"tm": "TM23"
				},
				{
					"move": "Thunderbolt",
					"tm": "TM24"
				},
				{
					"move": "Thunder",
					"tm": "TM25"
				},
				{
					"move": "Earthquake",
					"tm": "TM26"
				},
				{
					"move": "Return",
					"tm": "TM27"
				},
				{
					"move": "Psychic",
					"tm": "TM29"
				},
				{
					"move": "Shadow Ball",
					"tm": "TM30"
				},
				{
					"move": "Double Team",
					"tm": "TM32"
				},
				{
					"move": "Reflect",
					"tm": "TM33"
				},
				{
					"move": "Shock Wave",
					"tm": "TM34"
				},
				{
					"move": "Facade",
					"tm": "TM42"
				},
				{
					"move": "Secret Power",
					"tm": "TM43"
				},
				{
					"move": "Rest",
					"tm": "TM44"
				},
				{
					"move": "Attract",
					"tm": "TM45"
				},
				{
					"move": "Thief",
					"tm": "TM46"
				},
				{
					"move": "Skill Swap",
					"tm": "TM48"
				},
				{
					"move": "Energy Ball",
					"tm": "TM53"
				},
				{
					"move": "Charge Beam",
					"tm": "TM57"
				},
				{
					"move": "Endure",
					"tm": "TM58"
				},
				{
					"move": "Recycle",
					"tm": "TM67"
				},
				{
					"move": "Flash",
					"tm": "TM70"
				},
				{
					"move": "Thunder Wave",
					"tm": "TM73"
				},
				{
					"move": "Psych Up",
					"tm": "TM77"
				},
				{
					"move": "Captivate",
					"tm": "TM78"
				},
				{
					"move": "Sleep Talk",
					"tm": "TM82"
				},
				{
					"move": "Natural Gift",
					"tm": "TM83"
				},
				{
					"move": "Dream Eater",
					"tm": "TM85"
				},
				{
					"move": "Grass Knot",
					"tm": "TM86"
				},
				{
					"move": "Swagger",
					"tm": "TM87"
				},
				{
					"move": "Substitute",
					"tm": "TM90"
				},
				{
					"move": "Trick Room",
					"tm": "TM92"
				}
			]
		},
		{
			"games": [
				"Platinum"
			],
			"learnset": [
				{
					"move": "Astonish",
					"level": 1
				},
				{
					"move": "Confusion",
					"level": 1
				},
				{
					"move": "Growl",
					"level": 1
				},
				{
					"move": "Guard Swap",
					"level": 1
				},
				{
					"move": "Power Swap",
					"level": 1
				},
				{
					"move": "Tackle",
					"level": 1
				},
				{
					"move": "Odor Sleuth",
					"level": 5
				},
				{
					"move": "Stomp",
					"level": 10
				},
				{
					"move": "Agility",
					"level": 14
				},
				{
					"move": "Psybeam",
					"level": 19
				},
				{
					"move": "Baton Pass",
					"level": 23
				},
				{
					"move": "Assurance",
					"level": 28
				},
				{
					"move": "Double Hit",
					"level": 32
				},
				{
					"move": "Psychic",
					"level": 37
				},
				{
					"move": "Zen Headbutt",
					"level": 41
				},
				{
					"move": "Crunch",
					"level": 46
				},
				{
					"move": "Amnesia",
					"egg_move": true
				},
				{
					"move": "Beat Up",
					"egg_move": true
				},
				{
					"move": "Double Kick",
					"egg_move": true
				},
				{
					"move": "Foresight",
					"egg_move": true
				},
				{
					"move": "Future Sight",
					"egg_move": true
				},
				{
					"move": "Magic Coat",
					"egg_move": true
				},
				{
					"move": "Mirror Coat",
					"egg_move": true
				},
				{
					"move": "Psych Up",
					"egg_move": true
				},
				{
					"move": "Take Down",
					"egg_move": true
				},
				{
					"move": "Wish",
					"egg_move": true
				},
				{
					"move": "Strength",
					"tm": "HM4"
				},
				{
					"move": "Rock Smash",
					"tm": "HM6"
				},
				{
					"move": "Calm Mind",
					"tm": "TM4"
				},
				{
					"move": "Toxic",
					"tm": "TM6"
				},
				{
					"move": "Hidden Power",
					"tm": "TM10"
				},
				{
					"move": "Sunny Day",
					"tm": "TM11"
				},
				{
					"move": "Light Screen",
					"tm": "TM16"
				},
				{
					"move": "Protect",
					"tm": "TM17"
				},
				{
					"move": "Rain Dance",
					"tm": "TM18"
				},
				{
					"move": "Frustration",
					"tm": "TM21"
				},
				{
					"move": "Iron Tail",
					"tm": "TM23"
				},
				{
					"move": "Thunderbolt",
					"tm": "TM24"
				},
				{
					"move": "Thunder",
					"tm": "TM25"
				},
				{
					"move": "Earthquake",
					"tm": "TM26"
				},
				{
					"move": "Return",
					"tm": "TM27"
				},
				{
					"move": "Psychic",
					"tm": "TM29"
				},
				{
					"move": "Shadow Ball",
					"tm": "TM30"
				},
				{
					"move": "Double Team",
					"tm": "TM32"
				},
				{
					"move": "Reflect",
					"tm": "TM33"
				},
				{
					"move": "Shock Wave",
					"tm": "TM34"
				},
				{
					"move": "Facade",
					"tm": "TM42"
				},
				{
					"move": "Secret Power",
					"tm": "TM43"
				},
				{
					"move": "Rest",
					"tm": "TM44"
				},
				{
					"move": "Attract",
					"tm": "TM45"
				},
				{
					"move": "Thief",
					"tm": "TM46"
				},
				{
					"move": "Skill Swap",
					"tm": "TM48"
				},
				{
					"move": "Energy Ball",
					"tm": "TM53"
				},
				{
					"move": "Charge Beam",
					"tm": "TM57"
				},
				{
					"move": "Endure",
					"tm": "TM58"
				},
				{
					"move": "Recycle",
					"tm": "TM67"
				},
				{
					"move": "Flash",
					"tm": "TM70"
				},
				{
					"move": "Thunder Wave",
					"tm": "TM73"
				},
				{
					"move": "Psych Up",
					"tm": "TM77"
				},
				{
					"move": "Captivate",
					"tm": "TM78"
				},
				{
					"move": "Sleep Talk",
					"tm": "TM82"
				},
				{
					"move": "Natural Gift",
					"tm": "TM83"
				},
				{
					"move": "Dream Eater",
					"tm": "TM85"
				},
				{
					"move": "Grass Knot",
					"tm": "TM86"
				},
				{
					"move": "Swagger",
					"tm": "TM87"
				},
				{
					"move": "Substitute",
					"tm": "TM90"
				},
				{
					"move": "Trick Room",
					"tm": "TM92"
				}
			]
		},
		{
			"games": [
				"HeartGold",
				"SoulSilver"
			],
			"learnset": [
				{
					"move": "Astonish",
					"level": 1
				},
				{
					"move": "Confusion",
					"level": 1
				},
				{
					"move": "Growl",
					"level": 1
				},
				{
					"move": "Guard Swap",
					"level": 1
				},
				{
					"move": "Power Swap",
					"level": 1
				},
				{
					"move": "Tackle",
					"level": 1
				},
				{
					"move": "Odor Sleuth",
					"level": 5
				},
				{
					"move": "Stomp",
					"level": 10
				},
				{
					"move": "Agility",
					"level": 14
				},
				{
					"move": "Psybeam",
					"level": 19
				},
				{
					"move": "Baton Pass",
					"level": 23
				},
				{
					"move": "Assurance",
					"level": 28
				},
				{
					"move": "Double Hit",
					"level": 32
				},
				{
					"move": "Psychic",
					"level": 37
				},
				{
					"move": "Zen Headbutt",
					"level": 41
				},
				{
					"move": "Crunch",
					"level": 46
				},
				{
					"move": "Amnesia",
					"egg_move": true
				},
				{
					"move": "Beat Up",
					"egg_move": true
				},
				{
					"move": "Double Kick",
					"egg_move": true
				},
				{
					"move": "Foresight",
					"egg_move": true
				},
				{
					"move": "Future Sight",
					"egg_move": true
				},
				{
					"move": "Magic Coat",
					"egg_move": true
				},
				{
					"move": "Mirror Coat",
					"egg_move": true
				},
				{
					"move": "Psych Up",
					"egg_move": true
				},
				{
					"move": "Razor Wind",
					"egg_move": true
				},
				{
					"move": "Take Down",
					"egg_move": true
				},
				{
					"move": "Wish",
					"egg_move": true
				},
				{
					"move": "Strength",
					"tm": "HM4"
				},
				{
					"move": "Rock Smash",
					"tm": "HM6"
				},
				{
					"move": "Calm Mind",
					"tm": "TM4"
				},
				{
					"move": "Toxic",
					"tm": "TM6"
				},
				{
					"move": "Hidden Power",
					"tm": "TM10"
				},
				{
					"move": "Sunny Day",
					"tm": "TM11"
				},
				{
					"move": "Light Screen",
					"tm": "TM16"
				},
				{
					"move": "Protect",
					"tm": "TM17"
				},
				{
					"move": "Rain Dance",
					"tm": "TM18"
				},
				{
					"move": "Frustration",
					"tm": "TM21"
				},
				{
					"move": "Iron Tail",
					"tm": "TM23"
				},
				{
					"move": "Thunderbolt",
					"tm": "TM24"
				},
				{
					"move": "Thunder",
					"tm": "TM25"
				},
				{
					"move": "Earthquake",
					"tm": "TM26"
				},
				{
					"move": "Return",
					"tm": "TM27"
				},
				{
					"move": "Psychic",
					"tm": "TM29"
				},
				{
					"move": "Shadow Ball",
					"tm": "TM30"
				},
				{
					"move": "Double Team",
					"tm": "TM32"
				},
				{
					"move": "Reflect",
					"tm": "TM33"
				},
				{
					"move": "Shock Wave",
					"tm": "TM34"
				},
				{
					"move": "Facade",
					"tm": "TM42"
				},
				{
					"move": "Secret Power",
					"tm": "TM43"
				},
				{
					"move": "Rest",
					"tm": "TM44"
				},
				{
					"move": "Attract",
					"tm": "TM45"
				},
				{
					"move": "Thief",
					"tm": "TM46"
				},
				{
					"move": "Skill Swap",
					"tm": "TM48"
				},
				{
					"move": "Energy Ball",
					"tm": "TM53"
				},
				{
					"move": "Charge Beam",
					"tm": "TM57"
				},
				{
					"move": "Endure",
					"tm": "TM58"
				},
				{
					"move": "Recycle",
					"tm": "TM67"
				},
				{
					"move": "Flash",
					"tm": "TM70"
				},
				{
					"move": "Thunder Wave",
					"tm": "TM73"
				},
				{
					"move": "Psych Up",
					"tm": "TM77"
				},
				{
					"move": "Captivate",
					"tm": "TM78"
				},
				{
					"move": "Sleep Talk",
					"tm": "TM82"
				},
				{
					"move": "Natural Gift",
					"tm": "TM83"
				},
				{
					"move": "Dream Eater",
					"tm": "TM85"
				},
				{
					"move": "Grass Knot",
					"tm": "TM86"
				},
				{
					"move": "Swagger",
					"tm": "TM87"
				},
				{
					"move": "Substitute",
					"tm": "TM90"
				},
				{
					"move": "Trick Room",
					"tm": "TM92"
				}
			]
		},
		{
			"games": [
				"Black",
				"White"
			],
			"learnset": [
				{
					"move": "Astonish",
					"level": 1
				},
				{
					"move": "Confusion",
					"level": 1
				},
				{
					"move": "Growl",
					"level": 1
				},
				{
					"move": "Guard Swap",
					"level": 1
				},
				{
					"move": "Power Swap",
					"level": 1
				},
				{
					"move": "Tackle",
					"level": 1
				},
				{
					"move": "Odor Sleuth",
					"level": 5
				},
				{
					"move": "Stomp",
					"level": 10
				},
				{
					"move": "Agility",
					"level": 14
				},
				{
					"move": "Psybeam",
					"level": 19
				},
				{
					"move": "Baton Pass",
					"level": 23
				},
				{
					"move": "Assurance",
					"level": 28
				},
				{
					"move": "Double Hit",
					"level": 32
				},
				{
					"move": "Psychic",
					"level": 37
				},
				{
					"move": "Zen Headbutt",
					"level": 41
				},
				{
					"move": "Crunch",
					"level": 46
				},
				{
					"move": "Amnesia",
					"egg_move": true
				},
				{
					"move": "Beat Up",
					"egg_move": true
				},
				{
					"move": "Double Kick",
					"egg_move": true
				},
				{
					"move": "Foresight",
					"egg_move": true
				},
				{
					"move": "Future Sight",
					"egg_move": true
				},
				{
					"move": "Magic Coat",
					"egg_move": true
				},
				{
					"move": "Mean Look",
					"egg_move": true
				},
				{
					"move": "Mirror Coat",
					"egg_move": true
				},
				{
					"move": "Razor Wind",
					"egg_move": true
				},
				{
					"move": "Secret Power",
					"egg_move": true
				},
				{
					"move": "Skill Swap",
					"egg_move": true
				},
				{
					"move": "Take Down",
					"egg_move": true
				},
				{
					"move": "Wish",
					"egg_move": true
				},
				{
					"move": "Strength",
					"tm": "HM4"
				},
				{
					"move": "Psyshock",
					"tm": "TM3"
				},
				{
					"move": "Calm Mind",
					"tm": "TM4"
				},
				{
					"move": "Toxic",
					"tm": "TM6"
				},
				{
					"move": "Hidden Power",
					"tm": "TM10"
				},
				{
					"move": "Sunny Day",
					"tm": "TM11"
				},
				{
					"move": "Light Screen",
					"tm": "TM16"
				},
				{
					"move": "Protect",
					"tm": "TM17"
				},
				{
					"move": "Rain Dance",
					"tm": "TM18"
				},
				{
					"move": "Telekinesis",
					"tm": "TM19"
				},
				{
					"move": "Frustration",
					"tm": "TM21"
				},
				{
					"move": "Thunderbolt",
					"tm": "TM24"
				},
				{
					"move": "Thunder",
					"tm": "TM25"
				},
				{
					"move": "Earthquake",
					"tm": "TM26"
				},
				{
					"move": "Return",
					"tm": "TM27"
				},
				{
					"move": "Psychic",
					"tm": "TM29"
				},
				{
					"move": "Shadow Ball",
					"tm": "TM30"
				},
				{
					"move": "Double Team",
					"tm": "TM32"
				},
				{
					"move": "Reflect",
					"tm": "TM33"
				},
				{
					"move": "Facade",
					"tm": "TM42"
				},
				{
					"move": "Rest",
					"tm": "TM44"
				},
				{
					"move": "Attract",
					"tm": "TM45"
				},
				{
					"move": "Thief",
					"tm": "TM46"
				},
				{
					"move": "Round",
					"tm": "TM48"
				},
				{
					"move": "Echoed Voice",
					"tm": "TM49"
				},
				{
					"move": "Energy Ball",
					"tm": "TM53"
				},
				{
					"move": "Charge Beam",
					"tm": "TM57"
				},
				{
					"move": "Retaliate",
					"tm": "TM67"
				},
				{
					"move": "Flash",
					"tm": "TM70"
				},
				{
					"move": "Thunder Wave",
					"tm": "TM73"
				},
				{
					"move": "Psych Up",
					"tm": "TM77"
				},
				{
					"move": "Bulldoze",
					"tm": "TM78"
				},
				{
					"move": "Work Up",
					"tm": "TM83"
				},
				{
					"move": "Dream Eater",
					"tm": "TM85"
				},
				{
					"move": "Grass Knot",
					"tm": "TM86"
				},
				{
					"move": "Swagger",
					"tm": "TM87"
				},
				{
					"move": "Substitute",
					"tm": "TM90"
				},
				{
					"move": "Trick Room",
					"tm": "TM92"
				},
				{
					"move": "Rock Smash",
					"tm": "TM94"
				}
			]
		},
		{
			"games": [
				"Black 2",
				"White 2"
			],
			"learnset": [
				{
					"move": "Astonish",
					"level": 1
				},
				{
					"move": "Confusion",
					"level": 1
				},
				{
					"move": "Growl",
					"level": 1
				},
				{
					"move": "Guard Swap",
					"level": 1
				},
				{
					"move": "Power Swap",
					"level": 1
				},
				{
					"move": "Tackle",
					"level": 1
				},
				{
					"move": "Odor Sleuth",
					"level": 5
				},
				{
					"move": "Stomp",
					"level": 10
				},
				{
					"move": "Agility",
					"level": 14
				},
				{
					"move": "Psybeam",
					"level": 19
				},
				{
					"move": "Baton Pass",
					"level": 23
				},
				{
					"move": "Assurance",
					"level": 28
				},
				{
					"move": "Double Hit",
					"level": 32
				},
				{
					"move": "Psychic",
					"level": 37
				},
				{
					"move": "Zen Headbutt",
					"level": 41
				},
				{
					"move": "Crunch",
					"level": 46
				},
				{
					"move": "Amnesia",
					"egg_move": true
				},
				{
					"move": "Beat Up",
					"egg_move": true
				},
				{
					"move": "Double Kick",
					"egg_move": true
				},
				{
					"move": "Foresight",
					"egg_move": true
				},
				{
					"move": "Future Sight",
					"egg_move": true
				},
				{
					"move": "Magic Coat",
					"egg_move": true
				},
				{
					"move": "Mean Look",
					"egg_move": true
				},
				{
					"move": "Mirror Coat",
					"egg_move": true
				},
				{
					"move": "Razor Wind",
					"egg_move": true
				},
				{
					"move": "Secret Power",
					"egg_move": true
				},
				{
					"move": "Skill Swap",
					"egg_move": true
				},
				{
					"move": "Take Down",
					"egg_move": true
				},
				{
					"move": "Wish",
					"egg_move": true
				},
				{
					"move": "Strength",
					"tm": "HM4"
				},
				{
					"move": "Psyshock",
					"tm": "TM3"
				},
				{
					"move": "Calm Mind",
					"tm": "TM4"
				},
				{
					"move": "Toxic",
					"tm": "TM6"
				},
				{
					"move": "Hidden Power",
					"tm": "TM10"
				},
				{
					"move": "Sunny Day",
					"tm": "TM11"
				},
				{
					"move": "Light Screen",
					"tm": "TM16"
				},
				{
					"move": "Protect",
					"tm": "TM17"
				},
				{
					"move": "Rain Dance",
					"tm": "TM18"
				},
				{
					"move": "Telekinesis",
					"tm": "TM19"
				},
				{
					"move": "Frustration",
					"tm": "TM21"
				},
				{
					"move": "Thunderbolt",
					"tm": "TM24"
				},
				{
					"move": "Thunder",
					"tm": "TM25"
				},
				{
					"move": "Earthquake",
					"tm": "TM26"
				},
				{
					"move": "Return",
					"tm": "TM27"
				},
				{
					"move": "Psychic",
					"tm": "TM29"
				},
				{
					"move": "Shadow Ball",
					"tm": "TM30"
				},
				{
					"move": "Double Team",
					"tm": "TM32"
				},
				{
					"move": "Reflect",
					"tm": "TM33"
				},
				{
					"move": "Facade",
					"tm": "TM42"
				},
				{
					"move": "Rest",
					"tm": "TM44"
				},
				{
					"move": "Attract",
					"tm": "TM45"
				},
				{
					"move": "Thief",
					"tm": "TM46"
				},
				{
					"move": "Round",
					"tm": "TM48"
				},
				{
					"move": "Echoed Voice",
					"tm": "TM49"
				},
				{
					"move": "Energy Ball",
					"tm": "TM53"
				},
				{
					"move": "Charge Beam",
					"tm": "TM57"
				},
				{
					"move": "Retaliate",
					"tm": "TM67"
				},
				{
					"move": "Flash",
					"tm": "TM70"
				},
				{
					"move": "Thunder Wave",
					"tm": "TM73"
				},
				{
					"move": "Psych Up",
					"tm": "TM77"
				},
				{
					"move": "Bulldoze",
					"tm": "TM78"
				},
				{
					"move": "Work Up",
					"tm": "TM83"
				},
				{
					"move": "Dream Eater",
					"tm": "TM85"
				},
				{
					"move": "Grass Knot",
					"tm": "TM86"
				},
				{
					"move": "Swagger",
					"tm": "TM87"
				},
				{
					"move": "Substitute",
					"tm": "TM90"
				},
				{
					"move": "Trick Room",
					"tm": "TM92"
				},
				{
					"move": "Rock Smash",
					"tm": "TM94"
				}
			]
		},
		{
			"games": [
				"X",
				"Y"
			],
			"learnset": [
				{
					"move": "Astonish",
					"level": 1
				},
				{
					"move": "Confusion",
					"level": 1
				},
				{
					"move": "Growl",
					"level": 1
				},
				{
					"move": "Guard Swap",
					"level": 1
				},
				{
					"move": "Power Swap",
					"level": 1
				},
				{
					"move": "Tackle",
					"level": 1
				},
				{
					"move": "Odor Sleuth",
					"level": 5
				},
				{
					"move": "Stomp",
					"level": 10
				},
				{
					"move": "Agility",
					"level": 14
				},
				{
					"move": "Psybeam",
					"level": 19
				},
				{
					"move": "Baton Pass",
					"level": 23
				},
				{
					"move": "Assurance",
					"level": 28
				},
				{
					"move": "Double Hit",
					"level": 32
				},
				{
					"move": "Psychic",
					"level": 37
				},
				{
					"move": "Zen Headbutt",
					"level": 41
				},
				{
					"move": "Crunch",
					"level": 46
				},
				{
					"move": "Amnesia",
					"egg_move": true
				},
				{
					"move": "Beat Up",
					"egg_move": true
				},
				{
					"move": "Double Kick",
					"egg_move": true
				},
				{
					"move": "Foresight",
					"egg_move": true
				},
				{
					"move": "Future Sight",
					"egg_move": true
				},
				{
					"move": "Magic Coat",
					"egg_move": true
				},
				{
					"move": "Mean Look",
					"egg_move": true
				},
				{
					"move": "Mirror Coat",
					"egg_move": true
				},
				{
					"move": "Razor Wind",
					"egg_move": true
				},
				{
					"move": "Secret Power",
					"egg_move": true
				},
				{
					"move": "Skill Swap",
					"egg_move": true
				},
				{
					"move": "Take Down",
					"egg_move": true
				},
				{
					"move": "Wish",
					"egg_move": true
				},
				{
					"move": "Strength",
					"tm": "HM4"
				},
				{
					"move": "Psyshock",
					"tm": "TM3"
				},
				{
					"move": "Calm Mind",
					"tm": "TM4"
				},
				{
					"move": "Toxic",
					"tm": "TM6"
				},
				{
					"move": "Hidden Power",
					"tm": "TM10"
				},
				{
					"move": "Sunny Day",
					"tm": "TM11"
				},
				{
					"move": "Light Screen",
					"tm": "TM16"
				},
				{
					"move": "Protect",
					"tm": "TM17"
				},
				{
					"move": "Rain Dance",
					"tm": "TM18"
				},
				{
					"move": "Frustration",
					"tm": "TM21"
				},
				{
					"move": "Thunderbolt",
					"tm": "TM24"
				},
				{
					"move": "Thunder",
					"tm": "TM25"
				},
				{
					"move": "Earthquake",
					"tm": "TM26"
				},
				{
					"move": "Return",
					"tm": "TM27"
				},
				{
					"move": "Psychic",
					"tm": "TM29"
				},
				{
					"move": "Shadow Ball",
					"tm": "TM30"
				},
				{
					"move": "Double Team",
					"tm": "TM32"
				},
				{
					"move": "Reflect",
					"tm": "TM33"
				},
				{
					"move": "Facade",
					"tm": "TM42"
				},
				{
					"move": "Rest",
					"tm": "TM44"
				},
				{
					"move": "Attract",
					"tm": "TM45"
				},
				{
					"move": "Thief",
					"tm": "TM46"
				},
				{
					"move": "Round",
					"tm": "TM48"
				},
				{
					"move": "Echoed Voice",
					"tm": "TM49"
				},
				{
					"move": "Energy Ball",
					"tm": "TM53"
				},
				{
					"move": "Charge Beam",
					"tm": "TM57"
				},
				{
					"move": "Retaliate",
					"tm": "TM67"
				},
				{
					"move": "Flash",
					"tm": "TM70"
				},
				{
					"move": "Thunder Wave",
					"tm": "TM73"
				},
				{
					"move": "Psych Up",
					"tm": "TM77"
				},
				{
					"move": "Bulldoze",
					"tm": "TM78"
				},
				{
					"move": "Dream Eater",
					"tm": "TM85"
				},
				{
					"move": "Grass Knot",
					"tm": "TM86"
				},
				{
					"move": "Swagger",
					"tm": "TM87"
				},
				{
					"move": "Sleep Talk",
					"tm": "TM88"
				},
				{
					"move": "Substitute",
					"tm": "TM90"
				},
				{
					"move": "Trick Room",
					"tm": "TM92"
				},
				{
					"move": "Rock Smash",
					"tm": "TM94"
				},
				{
					"move": "Dazzling Gleam",
					"tm": "TM99"
				},
				{
					"move": "Confide",
					"tm": "TM100"
				}
			]
		},
		{
			"games": [
				"Omega Ruby",
				"Alpha Sapphire"
			],
			"learnset": [
				{
					"move": "Astonish",
					"level": 1
				},
				{
					"move": "Confusion",
					"level": 1
				},
				{
					"move": "Growl",
					"level": 1
				},
				{
					"move": "Guard Swap",
					"level": 1
				},
				{
					"move": "Power Swap",
					"level": 1
				},
				{
					"move": "Tackle",
					"level": 1
				},
				{
					"move": "Odor Sleuth",
					"level": 5
				},
				{
					"move": "Assurance",
					"level": 10
				},
				{
					"move": "Stomp",
					"level": 14
				},
				{
					"move": "Psybeam",
					"level": 19
				},
				{
					"move": "Agility",
					"level": 23
				},
				{
					"move": "Double Hit",
					"level": 28
				},
				{
					"move": "Zen Headbutt",
					"level": 32
				},
				{
					"move": "Crunch",
					"level": 37
				},
				{
					"move": "Baton Pass",
					"level": 41
				},
				{
					"move": "Nasty Plot",
					"level": 46
				},
				{
					"move": "Psychic",
					"level": 50
				},
				{
					"move": "Amnesia",
					"egg_move": true
				},
				{
					"move": "Beat Up",
					"egg_move": true
				},
				{
					"move": "Double Kick",
					"egg_move": true
				},
				{
					"move": "Foresight",
					"egg_move": true
				},
				{
					"move": "Future Sight",
					"egg_move": true
				},
				{
					"move": "Magic Coat",
					"egg_move": true
				},
				{
					"move": "Mean Look",
					"egg_move": true
				},
				{
					"move": "Mirror Coat",
					"egg_move": true
				},
				{
					"move": "Razor Wind",
					"egg_move": true
				},
				{
					"move": "Secret Power",
					"egg_move": true
				},
				{
					"move": "Skill Swap",
					"egg_move": true
				},
				{
					"move": "Take Down",
					"egg_move": true
				},
				{
					"move": "Wish",
					"egg_move": true
				},
				{
					"move": "Strength",
					"tm": "HM4"
				},
				{
					"move": "Rock Smash",
					"tm": "HM6"
				},
				{
					"move": "Psyshock",
					"tm": "TM3"
				},
				{
					"move": "Calm Mind",
					"tm": "TM4"
				},
				{
					"move": "Toxic",
					"tm": "TM6"
				},
				{
					"move": "Hidden Power",
					"tm": "TM10"
				},
				{
					"move": "Sunny Day",
					"tm": "TM11"
				},
				{
					"move": "Light Screen",
					"tm": "TM16"
				},
				{
					"move": "Protect",
					"tm": "TM17"
				},
				{
					"move": "Rain Dance",
					"tm": "TM18"
				},
				{
					"move": "Frustration",
					"tm": "TM21"
				},
				{
					"move": "Thunderbolt",
					"tm": "TM24"
				},
				{
					"move": "Thunder",
					"tm": "TM25"
				},
				{
					"move": "Earthquake",
					"tm": "TM26"
				},
				{
					"move": "Return",
					"tm": "TM27"
				},
				{
					"move": "Psychic",
					"tm": "TM29"
				},
				{
					"move": "Shadow Ball",
					"tm": "TM30"
				},
				{
					"move": "Double Team",
					"tm": "TM32"
				},
				{
					"move": "Reflect",
					"tm": "TM33"
				},
				{
					"move": "Facade",
					"tm": "TM42"
				},
				{
					"move": "Rest",
					"tm": "TM44"
				},
				{
					"move": "Attract",
					"tm": "TM45"
				},
				{
					"move": "Thief",
					"tm": "TM46"
				},
				{
					"move": "Round",
					"tm": "TM48"
				},
				{
					"move": "Echoed Voice",
					"tm": "TM49"
				},
				{
					"move": "Energy Ball",
					"tm": "TM53"
				},
				{
					"move": "Charge Beam",
					"tm": "TM57"
				},
				{
					"move": "Retaliate",
					"tm": "TM67"
				},
				{
					"move": "Flash",
					"tm": "TM70"
				},
				{
					"move": "Thunder Wave",
					"tm": "TM73"
				},
				{
					"move": "Psych Up",
					"tm": "TM77"
				},
				{
					"move": "Bulldoze",
					"tm": "TM78"
				},
				{
					"move": "Dream Eater",
					"tm": "TM85"
				},
				{
					"move": "Grass Knot",
					"tm": "TM86"
				},
				{
					"move": "Swagger",
					"tm": "TM87"
				},
				{
					"move": "Sleep Talk",
					"tm": "TM88"
				},
				{
					"move": "Substitute",
					"tm": "TM90"
				},
				{
					"move": "Trick Room",
					"tm": "TM92"
				},
				{
					"move": "Secret Power",
					"tm": "TM94"
				},
				{
					"move": "Dazzling Gleam",
					"tm": "TM99"
				},
				{
					"move": "Confide",
					"tm": "TM100"
				}
			]
		},
		{
			"games": [
				"Sun",
				"Moon"
			],
			"learnset": [
				{
					"move": "Astonish",
					"level": 1
				},
				{
					"move": "Confusion",
					"level": 1
				},
				{
					"move": "Growl",
					"level": 1
				},
				{
					"move": "Guard Swap",
					"level": 1
				},
				{
					"move": "Power Swap",
					"level": 1
				},
				{
					"move": "Tackle",
					"level": 1
				},
				{
					"move": "Odor Sleuth",
					"level": 5
				},
				{
					"move": "Assurance",
					"level": 10
				},
				{
					"move": "Stomp",
					"level": 14
				},
				{
					"move": "Psybeam",
					"level": 19
				},
				{
					"move": "Agility",
					"level": 23
				},
				{
					"move": "Double Hit",
					"level": 28
				},
				{
					"move": "Zen Headbutt",
					"level": 32
				},
				{
					"move": "Crunch",
					"level": 37
				},
				{
					"move": "Baton Pass",
					"level": 41
				},
				{
					"move": "Nasty Plot",
					"level": 46
				},
				{
					"move": "Psychic",
					"level": 50
				},
				{
					"move": "Amnesia",
					"egg_move": true
				},
				{
					"move": "Beat Up",
					"egg_move": true
				},
				{
					"move": "Double Kick",
					"egg_move": true
				},
				{
					"move": "Foresight",
					"egg_move": true
				},
				{
					"move": "Future Sight",
					"egg_move": true
				},
				{
					"move": "Magic Coat",
					"egg_move": true
				},
				{
					"move": "Mean Look",
					"egg_move": true
				},
				{
					"move": "Mirror Coat",
					"egg_move": true
				},
				{
					"move": "Razor Wind",
					"egg_move": true
				},
				{
					"move": "Secret Power",
					"egg_move": true
				},
				{
					"move": "Skill Swap",
					"egg_move": true
				},
				{
					"move": "Take Down",
					"egg_move": true
				},
				{
					"move": "Wish",
					"egg_move": true
				},
				{
					"move": "Work Up",
					"tm": "TM1"
				},
				{
					"move": "Psyshock",
					"tm": "TM3"
				},
				{
					"move": "Calm Mind",
					"tm": "TM4"
				},
				{
					"move": "Toxic",
					"tm": "TM6"
				},
				{
					"move": "Hidden Power",
					"tm": "TM10"
				},
				{
					"move": "Sunny Day",
					"tm": "TM11"
				},
				{
					"move": "Light Screen",
					"tm": "TM16"
				},
				{
					"move": "Protect",
					"tm": "TM17"
				},
				{
					"move": "Rain Dance",
					"tm": "TM18"
				},
				{
					"move": "Frustration",
					"tm": "TM21"
				},
				{
					"move": "Thunderbolt",
					"tm": "TM24"
				},
				{
					"move": "Thunder",
					"tm": "TM25"
				},
				{
					"move": "Earthquake",
					"tm": "TM26"
				},
				{
					"move": "Return",
					"tm": "TM27"
				},
				{
					"move": "Psychic",
					"tm": "TM29"
				},
				{
					"move": "Shadow Ball",
					"tm": "TM30"
				},
				{
					"move": "Double Team",
					"tm": "TM32"
				},
				{
					"move": "Reflect",
					"tm": "TM33"
				},
				{
					"move": "Facade",
					"tm": "TM42"
				},
				{
					"move": "Rest",
					"tm": "TM44"
				},
				{
					"move": "Attract",
					"tm": "TM45"
				},
				{
					"move": "Thief",
					"tm": "TM46"
				},
				{
					"move": "Round",
					"tm": "TM48"
				},
				{
					"move": "Echoed Voice",
					"tm": "TM49"
				},
				{
					"move": "Energy Ball",
					"tm": "TM53"
				},
				{
					"move": "Charge Beam",
					"tm": "TM57"
				},
				{
					"move": "Thunder Wave",
					"tm": "TM73"
				},
				{
					"move": "Psych Up",
					"tm": "TM77"
				},
				{
					"move": "Bulldoze",
					"tm": "TM78"
				},
				{
					"move": "Dream Eater",
					"tm": "TM85"
				},
				{
					"move": "Grass Knot",
					"tm": "TM86"
				},
				{
					"move": "Swagger",
					"tm": "TM87"
				},
				{
					"move": "Sleep Talk",
					"tm": "TM88"
				},
				{
					"move": "Substitute",
					"tm": "TM90"
				},
				{
					"move": "Trick Room",
					"tm": "TM92"
				},
				{
					"move": "Dazzling Gleam",
					"tm": "TM99"
				},
				{
					"move": "Confide",
					"tm": "TM100"
				}
			]
		},
		{
			"games": [
				"Ultra Sun",
				"Ultra Moon"
			],
			"learnset": [
				{
					"move": "Astonish",
					"level": 1
				},
				{
					"move": "Confusion",
					"level": 1
				},
				{
					"move": "Growl",
					"level": 1
				},
				{
					"move": "Guard Swap",
					"level": 1
				},
				{
					"move": "Power Swap",
					"level": 1
				},
				{
					"move": "Tackle",
					"level": 1
				},
				{
					"move": "Odor Sleuth",
					"level": 5
				},
				{
					"move": "Assurance",
					"level": 10
				},
				{
					"move": "Stomp",
					"level": 14
				},
				{
					"move": "Psybeam",
					"level": 19
				},
				{
					"move": "Agility",
					"level": 23
				},
				{
					"move": "Double Hit",
					"level": 28
				},
				{
					"move": "Zen Headbutt",
					"level": 32
				},
				{
					"move": "Crunch",
					"level": 37
				},
				{
					"move": "Baton Pass",
					"level": 41
				},
				{
					"move": "Nasty Plot",
					"level": 46
				},
				{
					"move": "Psychic",
					"level": 50
				},
				{
					"move": "Amnesia",
					"egg_move": true
				},
				{
					"move": "Beat Up",
					"egg_move": true
				},
				{
					"move": "Double Kick",
					"egg_move": true
				},
				{
					"move": "Foresight",
					"egg_move": true
				},
				{
					"move": "Future Sight",
					"egg_move": true
				},
				{
					"move": "Magic Coat",
					"egg_move": true
				},
				{
					"move": "Mean Look",
					"egg_move": true
				},
				{
					"move": "Mirror Coat",
					"egg_move": true
				},
				{
					"move": "Psychic Fangs",
					"egg_move": true
				},
				{
					"move": "Psychic Terrain",
					"egg_move": true
				},
				{
					"move": "Razor Wind",
					"egg_move": true
				},
				{
					"move": "Secret Power",
					"egg_move": true
				},
				{
					"move": "Skill Swap",
					"egg_move": true
				},
				{
					"move": "Take Down",
					"egg_move": true
				},
				{
					"move": "Wish",
					"egg_move": true
				},
				{
					"move": "Work Up",
					"tm": "TM1"
				},
				{
					"move": "Psyshock",
					"tm": "TM3"
				},
				{
					"move": "Calm Mind",
					"tm": "TM4"
				},
				{
					"move": "Toxic",
					"tm": "TM6"
				},
				{
					"move": "Hidden Power",
					"tm": "TM10"
				},
				{
					"move": "Sunny Day",
					"tm": "TM11"
				},
				{
					"move": "Light Screen",
					"tm": "TM16"
				},
				{
					"move": "Protect",
					"tm": "TM17"
				},
				{
					"move": "Rain Dance",
					"tm": "TM18"
				},
				{
					"move": "Frustration",
					"tm": "TM21"
				},
				{
					"move": "Thunderbolt",
					"tm": "TM24"
				},
				{
					"move": "Thunder",
					"tm": "TM25"
				},
				{
					"move": "Earthquake",
					"tm": "TM26"
				},
				{
					"move": "Return",
					"tm": "TM27"
				},
				{
					"move": "Psychic",
					"tm": "TM29"
				},
				{
					"move": "Shadow Ball",
					"tm": "TM30"
				},
				{
					"move": "Double Team",
					"tm": "TM32"
				},
				{
					"move": "Reflect",
					"tm": "TM33"
				},
				{
					"move": "Facade",
					"tm": "TM42"
				},
				{
					"move": "Rest",
					"tm": "TM44"
				},
				{
					"move": "Attract",
					"tm": "TM45"
				},
				{
					"move": "Thief",
					"tm": "TM46"
				},
				{
					"move": "Round",
					"tm": "TM48"
				},
				{
					"move": "Echoed Voice",
					"tm": "TM49"
				},
				{
					"move": "Energy Ball",
					"tm": "TM53"
				},
				{
					"move": "Charge Beam",
					"tm": "TM57"
				},
				{
					"move": "Thunder Wave",
					"tm": "TM73"
				},
				{
					"move": "Psych Up",
					"tm": "TM77"
				},
				{
					"move": "Bulldoze",
					"tm": "TM78"
				},
				{
					"move": "Dream Eater",
					"tm": "TM85"
				},
				{
					"move": "Grass Knot",
					"tm": "TM86"
				},
				{
					"move": "Swagger",
					"tm": "TM87"
				},
				{
					"move": "Sleep Talk",
					"tm": "TM88"
				},
				{
					"move": "Substitute",
					"tm": "TM90"
				},
				{
					"move": "Trick Room",
					"tm": "TM92"
				},
				{
					"move": "Dazzling Gleam",
					"tm": "TM99"
				},
				{
					"move": "Confide",
					"tm": "TM100"
				}
			]
		}
	]
}
